expdb/__init__.py
expdb/cli.py
expdb/data/__init__.py
expdb/data/auth.py
expdb/data/models.py
expdb/packages/__init__.py
expdb/packages/expbin.py
expdb/packages/expcsv.py
expdb/packages/expjson.py
expdb/packages/expsql.py
expdb/utils/__init__.py
expdb/utils/readbin.py
tests/__init__.py
tests/data/__init__.py
tests/data/test_auth.py
tests/packages/__init__.py
tests/packages/test_expbin.py
tests/packages/test_expcsv.py
tests/packages/test_expjson.py
tests/packages/test_expsql.py
expdb-1.0.dist-info/LICENSE
expdb-1.0.dist-info/METADATA
expdb-1.0.dist-info/WHEEL
expdb-1.0.dist-info/entry_points.txt
expdb-1.0.dist-info/top_level.txt
expdb-1.0.dist-info/RECORD
