Metadata-Version: 2.1
Name: expdb
Version: 1.0
Summary: Python Library and CLI for exporting MySQL databases
Home-page: https://github.com/Devansh3712/expdb
Author: Devansh Singh
Author-email: devanshamity@gmail.com
License: MIT
Platform: UNKNOWN
Classifier: Programming Language :: Python :: 3
Classifier: License :: OSI Approved :: MIT License
Classifier: Operating System :: OS Independent
License-File: LICENSE
Requires-Dist: click (==8.0.3)
Requires-Dist: mysql (==0.0.3)
Requires-Dist: mysql-connector (==2.2.9)
Requires-Dist: mysqlclient (==2.1.0)
